fortune/__init__.py
fortune-1.1.1.dist-info/LICENSE.md
fortune-1.1.1.dist-info/METADATA
fortune-1.1.1.dist-info/WHEEL
fortune-1.1.1.dist-info/entry_points.txt
fortune-1.1.1.dist-info/top_level.txt
fortune-1.1.1.dist-info/RECORD
