Metadata-Version: 2.1
Name: fortune
Version: 1.1.1
Summary: Python version of old BSD Unix fortune program
Home-page: http://software.clapper.org/fortune/
Author: Brian M. Clapper
Author-email: bmc@clapper.org
License: BSD-style license
Classifier: Intended Audience :: End Users/Desktop
Classifier: Operating System :: OS Independent
Classifier: Topic :: Games/Entertainment
Classifier: License :: OSI Approved :: Apache Software License
Classifier: Programming Language :: Python
Classifier: Topic :: Text Processing :: Filters
License-File: LICENSE.md
Requires-Dist: grizzled-python (>=1.0)
